PQI/__init__.py
PQI/pqi.py
pqi-3.0.0.dist-info/LICENSE
pqi-3.0.0.dist-info/METADATA
pqi-3.0.0.dist-info/WHEEL
pqi-3.0.0.dist-info/entry_points.txt
pqi-3.0.0.dist-info/top_level.txt
pqi-3.0.0.dist-info/zip-safe
pqi-3.0.0.dist-info/RECORD
