Metadata-Version: 2.1
Name: pqi
Version: 3.0.0
Summary: Fast switching PyPi mirror image source
Home-page: https://github.com/yhangf/PyQuickInstall
Author: HangfengYang
Author-email: yhf5fhy@gmail.com
License: MIT
Keywords: python、PyPi source、terminal
License-File: LICENSE
Requires-Dist: docopt
